{
    "1": [
        "MACAN",
        "ASPHALT 8"
    ],
    "2": [
        "MONA",
        "Ты так мне необходим"
    ],
    "3": [
        "INSTASAMKA",
        "ЗА ДЕНЬГИ ДА"
    ],
    "4": [
        "Король и Шут",
        "Кукла колдуна"
    ],
    "5": [
        "Король и Шут",
        "Лесник"
    ],
    "6": [
        "LOVV66",
        "МАЙ МАЙ"
    ],
    "7": [
        "Andro",
        "Зари"
    ],
    "8": [
        "Король и Шут",
        "Прыгну со скалы"
    ],
    "9": [
        "A.V.G",
        "Ножевой"
    ],
    "10": [
        "Король и Шут",
        "Дурак и молния"
    ],
    "11": [
        "Король и Шут",
        "Камнем по голове"
    ],
    "12": [
        "Кравц",
        "Где прошла ты"
    ],
    "13": [
        "Miyagi & Эндшпиль",
        "По полям"
    ],
    "14": [
        "Король и Шут",
        "Танец злобного гения"
    ],
    "15": [
        "ANNA ASTI",
        "По барам"
    ],
    "16": [
        "Jakone",
        "По весне"
    ],
    "17": [
        "DVRST",
        "Komarovo"
    ],
    "18": [
        "XOLIDAYBOY",
        "Моя хулиганка"
    ],
    "19": [
        "Король и Шут",
        "Утренний рассвет"
    ],
    "20": [
        "Король и Шут",
        "Проклятый старый дом"
    ],
    "21": [
        "MOT",
        "Мурашками"
    ],
    "22": [
        "INSTASAMKA",
        "Отключаю телефон"
    ],
    "23": [
        "Daryana",
        "Заставлял"
    ],
    "24": [
        "xxxmanera",
        "Скажи мне кто ты"
    ],
    "25": [
        "Markul",
        "Стрелы"
    ],
    "26": [
        "OG Buda",
        "6AM в Будапеште"
    ],
    "27": [
        "Король и Шут",
        "Воспоминания о былой любви"
    ],
    "28": [
        "Slavik Pogosov",
        "Монро"
    ],
    "29": [
        "Король и Шут",
        "Мёртвый анархист"
    ],
    "30": [
        "Artik & Asti",
        "Кукла"
    ],
    "31": [
        "Король и Шут",
        "Ведьма и осёл"
    ],
    "32": [
        "INSTASAMKA",
        "Жара"
    ],
    "33": [
        "INSTASAMKA",
        "КАК MOMMY"
    ],
    "34": [
        "Каспийский Груз",
        "На белом"
    ],
    "35": [
        "ANNA ASTI",
        "Ночью на кухне"
    ],
    "36": [
        "Miyagi & Эндшпиль",
        "I Got Love"
    ],
    "37": [
        "OG Buda",
        "Касание"
    ],
    "38": [
        "Три дня дождя",
        "Отпускай"
    ],
    "39": [
        "Король и Шут",
        "Ели мясо мужики"
    ],
    "40": [
        "GAYAZOV$ BROTHER$",
        "МАЛИНОВАЯ ЛАДА"
    ],
    "41": [
        "ANNA ASTI",
        "Повело"
    ],
    "42": [
        "OG Buda",
        "Для Тебя (Пусто)"
    ],
    "43": [
        "Люся Чеботина",
        "ПЛАКАЛ ГОЛЛИВУД"
    ],
    "44": [
        "Keendy",
        "Не более"
    ],
    "45": [
        "Eminem",
        "Mockingbird"
    ],
    "46": [
        "DJ SMASH",
        "Позвони"
    ],
    "47": [
        "Монеточка",
        "Папина любовница"
    ],
    "48": [
        "OG Buda",
        "Сандэй Сервис"
    ],
    "49": [
        "Король и Шут",
        "Марионетки"
    ],
    "50": [
        "Amirchik",
        "Эта любовь"
    ],
    "51": [
        "Miyagi & Andy Panda",
        "Minor"
    ],
    "52": [
        "ЕГОР КРИД",
        "Засыпаешь, но не со мной"
    ],
    "53": [
        "Король и Шут",
        "Ром"
    ],
    "54": [
        "Jakone",
        "С тобой"
    ],
    "55": [
        "Баста",
        "Где ты теперь и с кем"
    ],
    "56": [
        "Miyagi & Andy Panda",
        "Там ревели горы"
    ],
    "57": [
        "BRANYA",
        "Пополам"
    ],
    "58": [
        "Король и Шут",
        "Тяни!"
    ],
    "59": [
        "Люся Чеботина",
        "Солнце Монако"
    ],
    "60": [
        "ANNA ASTI",
        "Хобби"
    ],
    "61": [
        "INSTASAMKA",
        "Тяги"
    ],
    "62": [
        "TEMNEE",
        "Однажды"
    ],
    "63": [
        "ХАБИБ",
        "Ягода малинка"
    ],
    "64": [
        "OG Buda",
        "Интересно"
    ],
    "65": [
        "INSTASAMKA",
        "POPSTAR"
    ],
    "66": [
        "YUNGWAY",
        "Магазин"
    ],
    "67": [
        "JONY",
        "Заворожённый"
    ],
    "68": [
        "Король и Шут",
        "Северный флот"
    ],
    "69": [
        "Гио Пика",
        "Листопадом"
    ],
    "70": [
        "kochneva",
        "прости"
    ],
    "71": [
        "Коста Лакоста",
        "Весна"
    ],
    "72": [
        "Big Baby Tape",
        "HOODAK MP3"
    ],
    "73": [
        "OG Buda",
        "Сердце </3 Время"
    ],
    "74": [
        "Антон Токарев",
        "Седьмой лепесток"
    ],
    "75": [
        "MACAN",
        "Кино"
    ],
    "76": [
        "Liili",
        "Hot"
    ],
    "77": [
        "LOVV66",
        "5IVE"
    ],
    "78": [
        "Порнофильмы",
        "Я так соскучился"
    ],
    "79": [
        "Артём Качер",
        "Один из двух"
    ],
    "80": [
        "Heronwater",
        "Одаривает (Prod. by Heronwater)"
    ],
    "81": [
        "Filatov & Karas",
        "Мимо меня"
    ],
    "82": [
        "Король и Шут",
        "Два друга и разбойники"
    ],
    "83": [
        "Лизогуб",
        "ДЕВОЧКА УЭНСДЕЙ"
    ],
    "84": [
        "Лолита",
        "По-другому"
    ],
    "85": [
        "Miyagi",
        "Captain"
    ],
    "86": [
        "Kamazz",
        "Как ты там"
    ],
    "87": [
        "Jah Khalib",
        "Доча"
    ],
    "88": [
        "Скриптонит",
        "Baby mama"
    ],
    "89": [
        "OG Buda",
        "Не думать"
    ],
    "90": [
        "Король и Шут",
        "Смельчак и ветер"
    ],
    "91": [
        "JONY",
        "Как любовь твою понять?"
    ],
    "92": [
        "Miyagi & Andy Panda",
        "Marmalade"
    ],
    "93": [
        "Artik & Asti",
        "Гармония"
    ],
    "94": [
        "Big Baby Tape",
        "Like A G6"
    ],
    "95": [
        "Aarne",
        "Тесно"
    ],
    "96": [
        "NЮ",
        "Некуда бежать"
    ],
    "97": [
        "Lady Gaga",
        "Bloody Mary"
    ],
    "98": [
        "HammAli & Navai",
        "Засыпай, красавица"
    ],
    "99": [
        "Люся Чеботина",
        "МОЁ"
    ],
    "100": [
        "Yanix",
        "Legacy"
    ]
}